CHANGELOG.txt
LICENCE.txt
MANIFEST.in
README.txt
calculate_price.py
cart.py
order.py
setup.py
subscription.py
kisaan-utils/__init__.py
kisaan-utils/area.py
kisaan_utils.egg-info/PKG-INFO
kisaan_utils.egg-info/SOURCES.txt
kisaan_utils.egg-info/dependency_links.txt
kisaan_utils.egg-info/requires.txt
kisaan_utils.egg-info/top_level.txt