Metadata-Version: 1.1
Name: kisaan-utils
Version: 0.0.3
Summary: A very basic discription
Home-page: UNKNOWN
Author: Joshua Lowe
Author-email: josh@edublocks.org
License: MIT
Keywords: kisaan
Platform: UNKNOWN
Classifier: Development Status :: 5 - Production/Stable
Classifier: Intended Audience :: Education
Classifier: Operating System :: Microsoft :: Windows :: Windows 10
Classifier: License :: OSI Approved :: MIT License
Classifier: Programming Language :: Python :: 3
